examples/__init__.py
examples/experiment/__init__.py
examples/experiment/comparison.py
examples/experiment/generateMedianAndWilcoxonLatexTables.py
examples/experiment/statistical_analysis.py
examples/multiobjective/__init__.py
examples/multiobjective/gde3/__init__.py
examples/multiobjective/gde3/dynamic_gde3.py
examples/multiobjective/gde3/gde3_spark_evaluator.py
examples/multiobjective/gde3/gde3_zdt1.py
examples/multiobjective/gde3/ggde3_zdt2.py
examples/multiobjective/hype/__init__.py
examples/multiobjective/hype/hype_zdt1.py
examples/multiobjective/ibea/__init__.py
examples/multiobjective/ibea/ibea_zdt1.py
examples/multiobjective/mocell/__init__.py
examples/multiobjective/mocell/mocell_zdt1.py
examples/multiobjective/moead/__init__.py
examples/multiobjective/moead/moead_dtlz2.py
examples/multiobjective/moead/moead_iepsilon_lircmop1.py
examples/multiobjective/moead/moead_lz09.py
examples/multiobjective/moead/moeaddra_lz09.py
examples/multiobjective/nsgaii/__init__.py
examples/multiobjective/nsgaii/distributed_nsgaii_with_dask.py
examples/multiobjective/nsgaii/distributed_nsgaii_with_dask_evaluator.py
examples/multiobjective/nsgaii/distributed_nsgaii_with_spark_evaluator.py
examples/multiobjective/nsgaii/dynamic_nsgaii_solving_fda2.py
examples/multiobjective/nsgaii/nsgaii_defining_schaffer_problem_on_the_fly.py
examples/multiobjective/nsgaii/nsgaii_defining_srinivas_problem_on_the_fly.py
examples/multiobjective/nsgaii/nsgaii_solving_3D_problem.py
examples/multiobjective/nsgaii/nsgaii_solving_binary_problem.py
examples/multiobjective/nsgaii/nsgaii_solving_constrained_srinivas_problem.py
examples/multiobjective/nsgaii/nsgaii_solving_mixed_encoding_problem.py
examples/multiobjective/nsgaii/nsgaii_ssp.py
examples/multiobjective/nsgaii/nsgaii_standard_settings.py
examples/multiobjective/nsgaii/nsgaii_standard_settings_with_real_time_plotting.py
examples/multiobjective/nsgaii/nsgaii_steady_state.py
jmetalpy-1.6.0.dist-info/LICENSE
jmetalpy-1.6.0.dist-info/METADATA
jmetalpy-1.6.0.dist-info/WHEEL
jmetalpy-1.6.0.dist-info/top_level.txt
jmetalpy-1.6.0.dist-info/RECORD
