Metadata-Version: 2.1
Name: jmetalpy
Version: 1.6.0
Summary: Python version of the jMetal framework
Home-page: https://github.com/jMetal/jMetalPy
Author: Antonio J. Nebro
Author-email: antonio@lcc.uma.es
License: MIT
Project-URL: Source, https://github.com/jMetal/jMetalPy
Project-URL: Tracker, https://github.com/jMetal/jMetalPy/issues
Classifier: Development Status :: 5 - Production/Stable
Classifier: Intended Audience :: Science/Research
Classifier: License :: OSI Approved :: MIT License
Classifier: Topic :: Scientific/Engineering :: Artificial Intelligence
Classifier: Programming Language :: Python :: 3.7
Classifier: Programming Language :: Python :: 3.8
Classifier: Programming Language :: Python :: 3.9
Requires-Python: >=3.7
License-File: LICENSE
Requires-Dist: tqdm
Requires-Dist: numpy (>=1.16.0)
Requires-Dist: pandas (>=0.24.2)
Requires-Dist: plotly (>=3.3.0)
Requires-Dist: matplotlib (>=3.0.2)
Requires-Dist: scipy (>=1.3.0)
Requires-Dist: statsmodels (>=0.9.0)
Provides-Extra: all
Requires-Dist: dask[complete] (>=1.2.2) ; extra == 'all'
Requires-Dist: distributed (>=1.28.1) ; extra == 'all'
Requires-Dist: pyspark (>=2.4.0) ; extra == 'all'
Requires-Dist: isort ; extra == 'all'
Requires-Dist: black ; extra == 'all'
Requires-Dist: mypy ; extra == 'all'
Requires-Dist: mockito ; extra == 'all'
Requires-Dist: PyHamcrest ; extra == 'all'
Provides-Extra: dev
Requires-Dist: isort ; extra == 'dev'
Requires-Dist: black ; extra == 'dev'
Requires-Dist: mypy ; extra == 'dev'
Provides-Extra: distributed
Requires-Dist: dask[complete] (>=1.2.2) ; extra == 'distributed'
Requires-Dist: distributed (>=1.28.1) ; extra == 'distributed'
Requires-Dist: pyspark (>=2.4.0) ; extra == 'distributed'
Provides-Extra: test
Requires-Dist: mockito ; extra == 'test'
Requires-Dist: PyHamcrest ; extra == 'test'
